seqdiag/__init__.py
seqdiag/builder.py
seqdiag/command.py
seqdiag/drawer.py
seqdiag/elements.py
seqdiag/metrics.py
seqdiag/parser.py
seqdiag/tests/test_generate_diagram.py
seqdiag/tests/test_rst_directives.py
seqdiag/tests/VLGothic/LICENSE
seqdiag/tests/VLGothic/LICENSE.en
seqdiag/tests/VLGothic/LICENSE_E.mplus
seqdiag/tests/VLGothic/LICENSE_J.mplus
seqdiag/tests/VLGothic/VL-Gothic-Regular.ttf
seqdiag/tests/diagrams/alt_block.diag
seqdiag/tests/diagrams/altblock.diag
seqdiag/tests/diagrams/diagram_class.diag
seqdiag/tests/diagrams/diagram_edge_length.diag
seqdiag/tests/diagrams/nested_altblock.diag
seqdiag/tests/diagrams/node_activated.diag
seqdiag/tests/diagrams/node_fontsize.diag
seqdiag/tests/diagrams/node_notes.diag
seqdiag/tests/diagrams/plugin_autoclass.diag
seqdiag/tests/diagrams/separators.diag
seqdiag/tests/diagrams/separators_in_subedge.diag
seqdiag/utils/__init__.py
seqdiag/utils/rst/__init__.py
seqdiag/utils/rst/directives.py
seqdiag/utils/rst/nodes.py
seqdiag-3.0.0.dist-info/LICENSE
seqdiag-3.0.0.dist-info/METADATA
seqdiag-3.0.0.dist-info/WHEEL
seqdiag-3.0.0.dist-info/entry_points.txt
seqdiag-3.0.0.dist-info/top_level.txt
seqdiag-3.0.0.dist-info/RECORD
